noisy.py
noisy-0.1.dist-info/DESCRIPTION.rst
noisy-0.1.dist-info/METADATA
noisy-0.1.dist-info/RECORD
noisy-0.1.dist-info/WHEEL
noisy-0.1.dist-info/metadata.json
noisy-0.1.dist-info/top_level.txt
