Metadata-Version: 2.0
Name: noisy
Version: 0.1
Summary: Noise of different colors
Home-page: UNKNOWN
Author: Frederik Rietdijk
Author-email: fridh@fridh.nl
License: UNKNOWN
Platform: UNKNOWN
Classifier: License :: OSI Approved :: BSD License
Classifier: Programming Language :: Python :: 2
Classifier: Programming Language :: Python :: 3
Classifier: Topic :: Scientific/Engineering
Requires-Dist: numpy
